appcommander/Screen.py
appcommander/Script.py
appcommander/__init__.py
appcommander/__main__.py
appcommander/create_screens.py
appcommander/file_input_output.py
appcommander/hardcoded.py
appcommander/helper.py
appcommander/plot_script_flow.py
appcommander/run_bash_code.py
appcommander/run_script.py
appcommander/screen_reading.py
appcommander/script_orientation.py
appcommander/text_parsing.py
appcommander/arg_parser/__init__.py
appcommander/arg_parser/arg_parser.py
appcommander/arg_parser/process_args.py
appcommander/at_bitfire_davdroid/__init__.py
appcommander/at_bitfire_davdroid/V4_2_6/App_input_data.py
appcommander/at_bitfire_davdroid/V4_2_6/Screen_flow.py
appcommander/at_bitfire_davdroid/V4_2_6/__init__.py
appcommander/at_bitfire_davdroid/V4_2_6/helper.py
appcommander/at_bitfire_davdroid/V4_2_6/screen_0.py
appcommander/at_bitfire_davdroid/V4_2_6/screen_1.py
appcommander/at_bitfire_davdroid/V4_2_6/screen_2.py
appcommander/at_bitfire_davdroid/V4_2_6/screen_3.py
appcommander/at_bitfire_davdroid/V4_2_6/screen_4.py
appcommander/at_bitfire_davdroid/V4_2_6/screen_5.py
appcommander/at_bitfire_davdroid/V4_2_6/screen_6.py
appcommander/at_bitfire_davdroid/V4_2_6/screen_7.py
appcommander/at_bitfire_davdroid/V4_2_6/screen_8.py
appcommander/org_torproject_android/__init__.py
appcommander/org_torproject_android/V16_6_3_RC_1/App_input_data.py
appcommander/org_torproject_android/V16_6_3_RC_1/Screen_flow.py
appcommander/org_torproject_android/V16_6_3_RC_1/__init__.py
appcommander/org_torproject_android/V16_6_3_RC_1/helper.py
appcommander/org_torproject_android/V16_6_3_RC_1/screen_0.py
appcommander/org_torproject_android/V16_6_3_RC_1/screen_1.py
appcommander/org_torproject_android/V16_6_3_RC_1/screen_2.py
appcommander/org_torproject_android/V16_6_3_RC_1/screen_3.py
appcommander/org_torproject_android/V16_6_3_RC_1/screen_4.py
appcommander/org_torproject_android/V16_6_3_RC_1/screen_5.py
appcommander/org_torproject_android/V16_6_3_RC_1/screen_6.py
appcommander-0.0.35.dist-info/METADATA
appcommander-0.0.35.dist-info/WHEEL
appcommander-0.0.35.dist-info/entry_points.txt
appcommander-0.0.35.dist-info/licence
appcommander-0.0.35.dist-info/top_level.txt
appcommander-0.0.35.dist-info/RECORD
