Metadata-Version: 2.1
Name: appcommander
Version: 0.0.35
Summary: Performs controlled Android app automation through UI.
Home-page: https://github.com/Hiveminds/appcommander
Author: a-t-0
Author-email: no-email@no-email.org
Maintainer: a-t-0
Maintainer-email: no-email@no-email.org
License: AGPLv3
Classifier: Development Status :: 2 - Pre-Alpha
Classifier: Environment :: Console
Classifier: Intended Audience :: Science/Research
Classifier: License :: OSI Approved :: GNU Affero General Public License v3
Classifier: Programming Language :: Python
Classifier: Programming Language :: Python :: 3
Classifier: Programming Language :: Python :: 3 :: Only
Classifier: Programming Language :: Python :: 3.10
Classifier: Topic :: Software Development :: User Interfaces
Requires-Python: >=3.10
License-File: licence
Requires-Dist: xmltodict
Requires-Dist: matplotlib
Requires-Dist: networkx
Requires-Dist: pyannotate
Requires-Dist: pytest-cov
Requires-Dist: typeguard
Requires-Dist: uiautomator
Requires-Dist: pyasn1
Requires-Dist: pyasn1-modules
Requires-Dist: pyOpenSSL
